wildfly/__init__.py
wildfly/wildfly.py
wildfly-0.0.2.dist-info/LICENSE
wildfly-0.0.2.dist-info/METADATA
wildfly-0.0.2.dist-info/WHEEL
wildfly-0.0.2.dist-info/top_level.txt
wildfly-0.0.2.dist-info/RECORD
